pebootloader/__init__.py
pebootloader/__log.py
pebootloader/boot.py
pebootloader/embed.py
peinjecter/__boot.py
peinjecter/__core.py
peinjecter/__init__.py
peinjecter/utils.py
peinjecter-1.0.0.dist-info/METADATA
peinjecter-1.0.0.dist-info/WHEEL
peinjecter-1.0.0.dist-info/RECORD
