Metadata-Version: 2.1
Name: peinjecter
Version: 1.0.0
Summary: PEInjecter is a Python library that allows you to inject any executable file into the call lifecycle of an exe. This can be useful for a variety of purposes, such as adding custom functionality to an existing program or modifying its behavior.
License: MIT
Author: jawide
Author-email: 596929059@qq.com
Requires-Python: >=3.10,<3.12
Classifier: License :: OSI Approved :: MIT License
Classifier: Programming Language :: Python :: 3
Classifier: Programming Language :: Python :: 3.10
Classifier: Programming Language :: Python :: 3.11
Requires-Dist: configloaders (>=2.2.2,<3.0.0)
Requires-Dist: pyinstaller (>=5.10.1,<6.0.0)
